Workbook

Sheet Sheet1
B2: Er. SUNIL KUMAR | I2: # 304, Village: Daria,
B3: SURVEYOR & LOSS ASSESSOR | I3: Near Railway Station, Chandigarh
B4: LICENCE NO: 73070 EXPIRY: 08.02.2028 | I4: Mobile: 098761-35253
B5: PAN NO: AQUPK1480C | I5: e-mail:- ksunilsurveyor@gmail.com
B8: Ref: | C8: SK/2025-26/OICL/116 | J8: Date: | K8: 19.02.2026
B10: PRIVATE & CONFIDENTIAL SURVEY REPORT
B11: The Report is issued by me as Licenced surveyor without prejudice in respect of cause, nature & extent of loss/damages and subject to the terms and conditions of Insurance Policy.
B12: 1 | C12: policy particulars
C13: INSURERS | F13: : | G13: The Oriental Insurance Co. Ltd. | J13: IDV= | K13: 1320000
C14: ADDRESS | F14: : | G14: BO: SCO-52, Sector-42C, Chandigarh | W14: 98131- | X14: Nitu | Y14: udaanaaa
G15: Case allotted by The Oriental Ins. Co. Ltd., RO: SVC, Sector-17, Chd. | W15: 64284
C16: COVER NOTE/POLICY NO. | F16: : | G16: 231203/31/2025/7146 | J16: Period: | K16: 22.03.2025 to 21.03.2026 | N16: 231390
C18: INSURED | F18: : | G18: Mr JAGDEEP KUMAR
C19: ADDRESS | F19: : | G19: 2563, Sector-9-11, Hissar | Q19: Gap Report with photos
C20: CONTACT NO. | F20: : | G20: 95967-72665 | Q20: NCB Verification
Q21: Previous Policy
C22: HPA WITH | F22: : | G22: SBI
B24: 2 | C24: Vehicle Particulars | F24: : | G24: RC Original Checked & Found In Order
C25: Registration No. | F25: : | G25: HR 20AY 7179
C26: Date of Registration issue | F26: : | G26: 12.04.2024
C27: Date of Registration expiry | F27: : | G27: 11.04.2039
G28: Physically Checked | I28: As Per RC | K28: As Per Ins.
C29: Chassis No | F29: : | G29: 033264 | I29: =G29 -> 033264 | K29: =G29 -> 033264
C30: Engine No | F30: : | G30: 172413 | I30: =G30 -> 172413 | K30: =G30 -> 172413
C31: Make & Year of Manufacturer | F31: : | G31: SKODA KUSHAQ STYLE 1.0 TSI AT/2023
C32: Type of Body | F32: : | G32: Saloon
C33: Class of Vehicle | F33: : | G33: LMVCAR
C34: Pre-Accident Condition | F34: : | G34: Stated to be normal road worthy
C35: Registered Laden Weight | F35: : | G35: ---------------- | J35: Fuel used: Petrol
C36: Unladen Weight | F36: : | G36: 1277 Kg | J36: Colour: | K36: C Steel
C37: Seating Capacity | F37: : | G37: 5
C38: Road Tax Paid Upto | F38: : | G38: LTT
C39: Name of Regd. Owner as per RC | F39: : | G39: =G18 -> Mr JAGDEEP KUMAR
B41: 3 | C41: DRIVER'S PARTICULARS | F41: : | G41: DL Original Checked & Found In Order
C42: Name of Driver | F42: : | G42: Mr JAGDEEP KUMAR | J42: DOB: | K42: 07.01.1985
C43: Address | F43: : | G43: Narnaund,
C44: City/State | F44: : | G44: Hisar/Haryana | J44: Country: | K44: INDIA
C45: LICENCE NO. | F45: : | G45: HR-21/52074 | I45: (HR-2120080018996)
C46: Date of issue | F46: : | G46: 15.01.2008
C47: Valid Till | F47: : | G47: 14.01.2028
C48: Issuing Authority | F48: : | G48: LA-Hansi (NT)
C49: Type of Licence | F49: : | G49: Permanent for LMV/MCWG only
B51: 4 | C51: ACCIDENT HISTORY
C52: Date of Accident | F52: : | G52: 13.02.2026 about 9:45 AM | N52: 13.02.2026
C53: Place of Accident | F53: : | G53: Sector-34, Chandigarh
B55: 5 | C55: DETAIL OF SURVEY
C56: Date of Allotment of Survey | F56: : | G56: 14.02.2026
C57: Date and Time of Survey | F57: : | G57: 16.02.2026 | H57: and onwards
C58: Date of Spot Survey Report Recd. | F58: : | G58: Spot Survey not done.
C59: Person Present at the Time of Survey | F59: : | G59: Repairer was present
B62: 6 | C62: PLACE OF SURVEY
C63: Workshop | F63: : | G63: M/s Krishna Auto Sales | J63: (Authorosed SKODA Dealer)
C64: Address | F64: : | G64: Plot No. 177-H, Ind. Area, Phase-I, Chandigarh
B66: 7 | C66: FIR DETAIL | F66: : | G66: Nil (As Per Claim Form)
B68: 8 | C68: INJURY/THIRD PARTY LOSS | F68: : | G68: Nil (As Per Claim Form)
B70: 9 | C70: CAUSE AND NATURE OF ACCIDENT
C71: As stated in the Claim Form,
C72: " Insured was going to his office. On the way, another vehicle hit Insured's car from back right side. "
B74: 10 | C74: OBERVATIONS/COMMENTS
C75: As per the instructions of The Oriental Insurance Co Ltd, RO:-Service Centre, Sector-17, Chandigarh. I visited the Repairer's workshop. The Vehicle was carefully inspected, its damages were noted and photographs taken. The Photographs in the Under Repair Condition were also taken. The damages are commensurate with the cause and nature of accident.
B77: 11 | C77: MAIN DAMAGES
C78: Bumper Rear, etc,etc. | N78: 2371.12
N79: 882.9
B80: 12 | C80: NOTES:
B81: 1 | C81: Case allotted by The Oriental Insurance Co Ltd, RO: Service Centre, Sector-17, Chandigarh
B82: 2 | C82: The loss of damage or liability has arisen proximately caused by the insured peril.
B83: 3 | C83: None of the exclusion under the policy has is caused loss of damage or liability.
B84: 4 | C84: The salvage of the vehicle has been destroyed/crushed in the presence of the Repairer.
B85: 5 | C85: Re-inspection too has been done by me. All the replacemnets of parts and repair job have been dully carried out.
B86: 6 | C86: At the time of survey, I talked with Insured and discussed about the loss. About the loss, Insured told me the same which is mentioned in the Claim Form.
B87: 7 | C87: Insured's vehicle has NIL DEPRECIATION Policy.
B89: 13 | C89: DETAIL OF ASSESSMENT
B91: CUBIC CAPACITY | F91: 999 | G91: SO, EXCESS CLAUSE (IN RS.) | J91: 1000
B92: LIFE OF VEHICLE ( IN YEARS ) | F92: 1.89 | G92: SO, DEP. ON METAL (IN %) | J92: =IF(F92<0.5,0,IF(F92<1,5,IF(F92<2,10,IF(F92<3,15,IF(F92<4,25,IF(F92<5,35,IF(F92<10,40,50))))))) -> 10
B93: GSTIN (IN %) FOR PARTS | F93: 18 | G93: GSTIN (IN %) FOR LABOUR | J93: 18
G95: GST 18% | H95: GST 18% | I95: GST 18%
B96: S.N. | C96: Parts Name | F96: Estimated | G96: Alld--Metal | H96: Alld-Plastic | I96: Alld--Glass
B97: 1 | C97: Ret Strip | F97: 284.75 | G97: N.A.
B98: 2 | C98: Foam | F98: 780.51 | G98: N.A.
B99: 3 | C99: Cover | F99: 1989.83 | H99: 1989.83
B100: 4 | C100: Cover | F100: 1740.68 | H100: 1740.68
B101: 5 | C101: Spoiler | F101: 1567.8 | G101: N.A.
B102: 6 | C102: Piece | F102: 186.44 | H102: 186.44
B103: 7 | C103: Piece | F103: 186.44 | G103: N.A.
B104: 8 | C104: Piece | F104: 509.32 | G104: N.A.
B105: 9 | C105: Piece | F105: 509.32 | G105: N.A.
B106: 10 | C106: Reflector | F106: 577.12 | H106: 577.12
B107: 11 | C107: Trim | F107: 411.02 | H107: 411.02
B108: 12 | C108: Bracket | F108: 74.58 | G108: N.A.
B109: 13 | C109: Sensor | F109: 885.59 | G109: N.A.
B110: 14 | C110: Washer | F110: 5.08 | G110: N.A.
B111: SUB TOTAL | F111: =SUM(F97:F110) -> 9708.48 | G111: =SUM(G97:G110) -> 0 | H111: =SUM(H97:H110) -> 4905.09 | I111: =SUM(I97:I110) -> 0
B112: 18 | C112: % ADD GST (9%CGST+9%SGST) | F112: =B112*F111/100 -> 1747.5264 | G112: =B112*G111/100 -> 0 | H112: =B112*H111/100 -> 882.9162 | I112: =18*I111/100 -> 0
B113: SUB TOTAL | F113: =SUM(F111:F112) -> 11456.006 | G113: =SUM(G111:G112) -> 0 | H113: =SUM(H111:H112) -> 5788.0062 | I113: =SUM(I111:I112) -> 0
B114: LESS DEPRECIATION:
B115: 0 | C115: % OF METAL & 0% OF PLASTIC | G115: 0 | H115: 0 | I115: 0
B116: NET FOR PARTS | F116: =F113 -> 11456.006 | G116: =G113-G115 -> 0 | H116: =H113-H115 -> 5788.0062 | I116: =I113-I115 -> 0
B117: TOTAL NET FOR PARTS | F117: =F116 -> 11456.006 | G117: =G116+H116+I116 -> 5788.0062
B119: TOTAL AMOUNT OF DEPRECIATION (In Rs): | G119: =G115+H115+J115+I115 -> 0
B121: LABOUR DETAIL
...

Sheet Sheet2
G3: MOTOR SURVEY REPORT
B7: INSURER | F7: =Sheet1!G13 -> The Oriental Insurance Co. Ltd.
B8: ADDRESS | F8: =Sheet1!G14 -> BO: SCO-52, Sector-42C, Chandigarh
F9: =Sheet1!G15 -> Case allotted by The Oriental Ins. Co. Ltd., RO: SVC, Sector-17, Chd.
B12: INSURED | F12: =Sheet1!G18 -> Mr JAGDEEP KUMAR
B14: VEHICLE REG. NO. | F14: =Sheet1!G25 -> HR 20AY 7179
B16: C.NOTE/POLICY NO. | F16: =Sheet1!G16 -> 231203/31/2025/7146
B18: PERIOD | F18: =Sheet1!K16 -> 22.03.2025 to 21.03.2026
B20: DATE OF LOSS | F20: =Sheet1!G52 -> 13.02.2026 about 9:45 AM
B28: PAYMENT TO BE MADE IN THE FAVOUR OF REPAIRER
B34: CLAIM NUMBER:- | F34: 230011/31/2026/000
B35: DSR ON DATED:
B43: REPORT SUBMITTED BY:
B47: Er. SUNIL KUMAR | G47: # 304, Village: Daria,
B48: SURVEYOR & LOSS ASSESSOR | G48: Near Railway Station, Chandigarh
B49: LICENCE NO: 73070 EXPIRY: 08.02.2028 | G49: Mobile: 098761-35253
B50: PAN NO: AQUPK1480C | G50: e-mail:- ksunilsurveyor@gmail.com

Sheet Sheet4
F2: The Oriental Insurance Co. Ltd.
F3: Head Office, A-25/27, Asaf Ali Road, New Delhi-110002
B7: Vehicle No.: | D7: =Sheet1!G25 -> HR 20AY 7179 | H7: OWNER Name: | J7: =Sheet1!G18 -> Mr JAGDEEP KUMAR
B9: Documents Check List
B11: 1 | C11: DEP./CASH RECIECPT
B12: 2 | C12: Insured Mobile No. on Claim Form /Intimation
B13: 3 | C13: Intimation Letter and Correspondence related to it.
B14: 4 | C14: Claim Form
B15: 5 | C15: Surveyor Appointment Letter
B16: 6 | C16: Policy Copy
B17: 7 | C17: DL
B18: 8 | C18: RC (Road Tax Receipt for Temp. RC)
B19: 9 | C19: Insured ID Proof
B20: 10 | C20: 64VB
B21: 11 | C21: NCB
B22: 12 | C22: Staisfaction Voucher
... B29: 19 | C29: Pre Inspection
B31: Photographs
B33: 1 | C33: Damage Photos
B34: 2 | C34: Under Repair Photo
B35: 3 | C35: Reinspection Photos
B37: Additional Documents for NET OF SALVAGE
B39: 1 | C39: Interim Report
B40: 2 | C40: Loan Statement From Bank
B41: 3 | C41: DL & RC Verification
B42: 4 | C42: Consent Letter from Insured
B43: 5 | C43: PAN Card
B44: 6 | C44: Invoice of Vehicle
B45: 7 | C45: Three Online quotes for wreck
B46: 8 | C46: Affidavit in case no DDR/FIR/SPOT
E49: PAYMENT MADE IN THE FAVOUR OF REPAIRER

Sheet Sheet3
F1: ANNEXURE II
D2: Surveyor's Performance Appraisal (SPA) Form
C3: (to be filled in by the Surveyor and submitted along with Survey Report)
B4: Office Code | H4: Policy No. | I4: =Sheet1!G16 -> 231203/31/2025/7146
B5: Name of Office/Address | H5: Insured | I5: =Sheet1!G18 -> Mr JAGDEEP KUMAR
B6: Name of Surveyor | E6: Mr SUNIL KUMAR | H6: Claim No.
B7: Survey Report No. | E7: =Sheet1!C8 -> SK/2025-26/OICL/116 | H7: IIISLA Membership No./
H8: IRDAI Licence No. | J8: 73070
H9: Valid Upto | J9: 08.02.2028
B11: 1 | C11: Date of Loss: | H11: =Sheet1!N52 -> 13.02.2026
B13: 2 | C13: Date of Appointment of Surveyor | H13: =Sheet1!G56 -> 14.02.2026
B15: 3. a | C15: Date of First Visit to site | H15: =Sheet1!G57 -> 16.02.2026
B17: b | C17: Date of Submission of 'Intial Loss Advice'
B19: 4 | C19: Dates of subsequent visits
B21: 5 | C21: Date of submission of Interim Report, if any
B23: 6 | C23: Date of submission of Final Report
B25: 7 | C25: Reasons for delay in submission of report, if any
B27: 8 | C27: Whether consent for assessment obtained from the Insured / Claimant | J27: Yes/No
B29: 9 | C29: Number of times documents were requisitioned from the Insured (excluding reminders)
C30: (if more than 2 times, reason thereof)
B32: 10 | C32: Remarks
B34: Place:_______________________
B35: Date:_______________________ | I35: (Signature of the Surveyor)
B39: For Office use:-
B41: (to be filed in by the Claim Officer alongside settlement of each claim)
C42: Parameters | H42: Primary Claim Dealin | K42: Score
H43: Officer
C44: Timely submission of survey report | K44: 1-10
C45: (Please refer to Policy for marking)
C47: Error free and unambiguous survey report- | K47: 1-10
C48: Fair assessment
C50: Quick Response to queries raised, if any | K50: 1-10
C51: Suggenstion for risk improvement | K51: 1-10
C52: Feedback from the customer | K52: 1-10
B54: Ten point scale - Outstanding being (10) and Poor being ( 1 ):
B56: Signature:
B57: Name:
B58: Designation:
B59: Office:
B60: Date:

Sheet Sheet5
C3: Er. SUNIL KUMAR | J3: # 304, Village: Daria,
C4: SURVEYOR & LOSS ASSESSOR | J4: Near Railway Station, Chandigarh
C5: LICENCE NO: 73070 EXPIRY: 08.02.2028 | J5: Mobile: 098761-35253
C6: PAN NO: AQUPK1480C | J6: E-mail: ksunilsurveyor@gmail.com
C10: Ref: | D10: =Sheet1!C8 -> SK/2025-26/OICL/116 | K10: Date: | L10: =Sheet1!K8 -> 19.02.2026
F12: SURVEY FEE BILL
C15: INSURED | G15: =Sheet1!G18 -> Mr JAGDEEP KUMAR
G16: =Sheet1!G19 -> 2563, Sector-9-11, Hissar
C18: INSURERS | G18: =Sheet1!G13 -> The Oriental Insurance Co. Ltd.
G19: =Sheet1!G14 -> BO: SCO-52, Sector-42C, Chandigarh
G20: =Sheet1!G15 -> Case allotted by The Oriental Ins. Co. Ltd., RO: SVC, Sector-17, Chd.
C22: VEHICLE/ITEM | G22: =Sheet1!G25 -> HR 20AY 7179
C23: Make & Year of Manufacturer | G23: =Sheet1!G31 -> SKODA KUSHAQ STYLE 1.0 TSI AT/2023
C25: C NOTE/POLICY NO. | G25: =Sheet1!G16 -> 231203/31/2025/7146 | J25: Period: | K25: =Sheet1!K16 -> 22.03.2025 to 21.03.2026
C28: SURVEY FEE | G28: Rs | H28: 1800
C30: CONVEYANCE CHARGES | G30: Rs | H30: 500
C32: PHOTOGRAPHS | G32: Rs | H32: 0
C33: (Digital Photographs)
C35: DAILY ALLOWANCE | G35: Rs | H35: 0
C37: MISCELLANEOUS | G37: Rs | H37: 0
H38: ----------------------
F39: TOTAL | G39: Rs | H39: =SUM(H28:H37) -> 2300
H40: ----------------------
C42: INLYAS CODE: | E42: GH0000046246
C45: FOR NEFT PAYMENT | J45: (SUNIL KUMAR)
C47: BANK ACCOUNT DETAILS
C48: BANK NAME: | E48: BANK OF INDIA
C49: A/C NUMBER: | E49: 620110110000751
C50: A/C TYPE: | E50: SAVING
C51: IFSC CODE: | E51: BKID0006201
C52: MICRO CODE: | E52: 160013003

Sheet Sheet6
B5: ITEM WISE BREAK UP DETAILS IN SETTLEMENT SHEET
B7: ITEM DESCRIPTION | D7: NET AMOUNT (AFTER DEP.) | E7: GST % | F7: GST AMOUNT
B8: Labour | D8: =Sheet1!I134 -> 13170 | E8: 18 | F8: =D8*E8/100 -> 2370.6
B9: Parts Metallic | D9: =Sheet1!G111 -> 0 | E9: 18 | F9: =D9*E9/100 -> 0
B10: Parts Metallic | D10: 0 | E10: 18 | F10: =D10*E10/100 -> 0
B11: Parts Non-Metallic | D11: =Sheet1!I111 -> 0 | E11: 18 | F11: =D11*E11/100 -> 0
B12: Plastic | D12: =Sheet1!H111 -> 4905.09 | E12: 18 | F12: =D12*E12/100 -> 882.9162
B13: Glass | D13: =Sheet1!J111 -> 0 | E13: 18 | F13: =D13*E13/100 -> 0
B14: Other | D14: 0 | E14: 0 | F14: =D14*E14/100 -> 0
B15: Less: Excess Clause @18% | D15: =-Sheet1!G144 -> -1000 | E15: 18 | F15: =D15*E15/100 -> -180
B16: Less: Salvage Amount @18% | D16: =-Sheet1!G147 -> -100 | E16: 18 | F16: =D16*E16/100 -> -18
C17: Total | D17: =D8+D9+D10+D11+D12+D13+D14+D15+D16 -> 16975.09 | F17: 0
C18: GST Excess | D18: 180
C19: GST Salvage | D19: 18
C20: G.TOTAL | D20: =D17+D18+D19 -> 17173.09 | F20: 0
B21: GST Amount Entered in Settlement Screen | F21: =SUM(F8:F20) -> 3055.5162
C22: Settle Amount | F22: GST
C23: =D20 -> 17173.09 | F23: =F21 -> 3055.5162
B24: EST_72 Ptovision in INLIAS | E24: Rs. | F24: =C23 -> 17173.09
B25: GST Amount Entered in Settlement Screen | E25: Rs. | F25: =F23 -> 3055.5162
B26: NET LIABILITY | E26: Rs. | F26: =F24+F25 -> 20228.606

Sheet Sheet7
B2: Er. SUNIL KUMAR | I2: # 304, Village: Daria,
B3: SURVEYOR & LOSS ASSESSOR | I3: Near Railway Station, Chandigarh
B4: LICENCE NO: 73070 EXPIRY: 08.02.2028 | I4: Mobile: 098761-35253
B5: PAN NO: AQUPK1480C | I5: e-mail:- ksunilsurveyor@gmail.com
B8: Ref: | C8: SK/2024-25/OICL/058 | J8: Date: | K8: 16.06.2024
B10: PRIVATE & CONFIDENTIAL MOTOR RE-INSPECTION SURVEY REPORT
B11: The report is issued by me as Licenced surveyor without prejudice in respect of cause, nature & extent of loss/damages and subject to the terms and conditions of Insurance Policy.
B13: To,
B14: The Oriental Insurance Co. Ltd.,
B15: RO: SVC, Sector-17, Chandigarh.
B17: Sub: | C17: Reinspection of | E17: CH 01CH 8815
C18: A/C | D18: Mr YUDHISHTER | H18: Date of Accident: | J18: 03.06.2024
C19: C. No. | D19: 242596/31/2024/TMP/185254 | G19: Period: | H19: 01.03.2024 to 28.02.2025
B21: Sir,
B22: In pursuance to the instructions received from your office, the undersigned went to the workshop, M/s RSA Dynamic Motors LLP, Zirakpur for re-inspection of the vehicle under claim. Undersigned inspected the vehicle on 13.06.2024 and arranged few photographs.
B24: Fllowing are the details:
B26: 1 | C26: Whether all parts allowed for replacement by final survey report have been actually been replaced
C27: with the new parts. The details are as under:
B29: S.N. | C29: Particulars | F29: Remarks | G29: Salvage
B30: 1 | C30: Frt Bumper | F30: Replaced | G30: Examined
B31: 2 | C31: Fender LH | F31: Replaced | G31: Examined
B32: 3 | C32: Fender Cladding LH | F32: Replaced | G32: Examined
B33: 4 | C33: Wheel Arch Frt LH Bumper | F33: Replaced | G33: Examined
B34: 5 | C34: Rear Bumper | F34: Replaced | G34: Examined
B35: 6 | C35: Tailgater Tail Lamp LH | F35: Replaced | G35: Examined
B36: 8 | C36: Bracket Frt LH | F36: Replaced | G36: Examined
B37: 9 | C37: Tail Lamp Outer LH | F37: Replaced | G37: Examined
B39: 2 | C39: Salvage:
C40: The salvage has been checked and found to contain the replaced parts.
B42: 3 | C42: Labour/Repair
C43: The Repair have been carried out as per final survey report and car was in proper running condition at
C44: the time of re-inspection.
B46: 4 | C46: Remarks
C47: In the view of above re-inspection, what is the total quantam of reduction in the liability. The reduction in liability is nil.
B49: The re-inspection report is " without prejudice"
B51: Thanking you
B55: Er. SUNIL KUMAR
B58: Enclosures:
B59: 1 | C59: Final survey report
B60: 2 | C60: Re-inspection report & photographs
B61: 3 | C61: Survey fee bill
B63: I have physically verified the following Major Assembilies:
B65: Chassis No. | D65: 13325
B66: Engine No. | D66: 13366

Sheet Sheet8
B3: SUMMARY ASSESSMENT FOR SETTLEMENT OF CLAIM
B5: SURVEY REPORT NO. | E5: : | F5: =Sheet1!C8 -> SK/2025-26/OICL/116
B6: CLAIM NO. ALLOTTED ONLINE BY DEALER | E6: : | F6: 242596/31/2025/TMPC/14752
B7: NAME OF INSURED | E7: : | F7: =Sheet1!G18 -> Mr JAGDEEP KUMAR
B8: POLICY NO. | E8: : | F8: =Sheet1!G16 -> 231203/31/2025/7146
B9: PERIOD OF INSURANCE | E9: : | F9: =Sheet1!K16 -> 22.03.2025 to 21.03.2026
B10: VEHICLE REGISTRATION NO. | E10: : | F10: =Sheet1!G25 -> HR 20AY 7179
B11: MAKE OF VEHICLE & MODEL | E11: : | F11: =Sheet1!G31 -> SKODA KUSHAQ STYLE 1.0 TSI AT/2023
B13: ACCIDENT PARTICULARS
B14: DATE & TIME OF ACCIDENT | E14: : | F14: =Sheet1!G52 -> 13.02.2026 about 9:45 AM
B15: PLACE OF ACCIDENT | E15: : | F15: =Sheet1!G53 -> Sector-34, Chandigarh
B16: POLICE REPORT- FIR/DDR NO. (IF ANY) | E16: : | F16: Nil ( As per Claim Form )
B18: CAUSE OF ACCIDENT
B19: =Sheet1!C72 -> " Insured was going to his office. On the way, another vehicle hit Insured's car from back right side. "
B21: DRIVING LICENCE PARTICULARS
B22: NAME OF DRIVER | E22: : | F22: =Sheet1!G42 -> Mr JAGDEEP KUMAR
B23: DRIVING LICENCE NO. | E23: : | F23: =Sheet1!G45 -> HR-21/52074
B24: VALIDITY OF THE LICENCE | E24: : | F24: =Sheet1!G47 -> 14.01.2028
B25: LICENCE ISSUING AUTHORITY | E25: : | F25: =Sheet1!G48 -> LA-Hansi (NT)
B26: TYPE OF LICENCE | E26: : | F26: =Sheet1!G49 -> Permanent for LMV/MCWG only
B28: TOTAL ESTIMATE OF LOSS (INCUDING LABOUR & PARTS) | F28: =Sheet1!F145 -> 82255.936
B30: DETAIL OF ASSESSMENT
B31: PARTS (METAL, RUBBER/GLASS & GLASS) | F31: =Sheet1!G117 -> 5788.0062
B32: INCLUDING VAT (IF APPLICABLE)
B33: LABOUR- R/R, CUTTING/WELDING, ETC. | F33: 960
B34: COST OF PAINT (IF ASSESSED SEPARATELY) | F34: 0
B35: PAINTING CHARGES | F35: =Sheet1!I128 -> 11680
B36: GST (ON LABOUR) | F36: =Sheet1!I135 -> 2370.6
B37: TOWING CHARGES IF ANY | F37: 0
B38: SALVAGE-IF DEDUCTABLE | F38: ='[1]Sheet1'!G145 -> 0
B39: EXCESS CLAUSE-DEDUCTABLE | F39: ='[1]Sheet1'!G142 -> 1000
B40: ANY OTHER ASSESSMENT (DIFF.) | F40: 0
B41: NET PAYABLE AMOUNT (in Rs) | F41: =Sheet1!G148 -> 20228.606
B43: DETAIL OF SURVEY FEE
B44: PROFESSIONAL FESS | E44: : | F44: 1500
B45: COVEYANCE & PHOTOGRAPHS CHARGES | E45: : | F45: =500+140 -> 640
B46: GST (IF CHARGEABLE) | E46: : | F46: 0
B47: NET PAYABLE | F47: 2140
B50: SIGNATURE OF SURVEYOR (WITH SEAL)
B54: FOR OFFICE USE:
B55: REMARKS/RECOMMENDATIONS | F55: AGREED & RECOMMENDED FOR
F56: Rs………………………………………
B58: SIGNATURE (Name & Designation) | F58: AUTHORISED SIGNATURE
